[
  {
    "hex": "#000000",
    "count": 2139
  },
  {
    "hex": "#333333",
    "count": 1501
  },
  {
    "hex": "#444D66",
    "count": 1230
  },
  {
    "hex": "#20124D",
    "count": 922
  },
  {
    "hex": "#FFFFFF",
    "count": 870
  },
  {
    "hex": "#1E1938",
    "count": 325
  },
  {
    "hex": "#8068FF",
    "count": 121
  },
  {
    "hex": "#68FF86",
    "count": 45
  },
  {
    "hex": "#FF4B4B",
    "count": 30
  },
  {
    "hex": "#8AFFBC",
    "count": 25
  },
  {
    "hex": "#888EA1",
    "count": 20
  },
  {
    "hex": "#B9FFC2",
    "count": 15
  },
  {
    "hex": "#7F56D9",
    "count": 12
  },
  {
    "hex": "#8C98B9",
    "count": 10
  },
  {
    "hex": "#674EA7",
    "count": 8
  },
  {
    "hex": "#F1F5FF",
    "count": 7
  },
  {
    "hex": "#DDDDDD",
    "count": 4
  },
  {
    "hex": "#F7F8FC",
    "count": 3
  },
  {
    "hex": "#FFDEDE",
    "count": 3
  },
  {
    "hex": "#F2EFFA",
    "count": 1
  },
  {
    "hex": "#8F79FF",
    "count": 1
  },
  {
    "hex": "#15132A",
    "count": 1
  },
  {
    "hex": "#2A195D",
    "count": 1
  },
  {
    "hex": "#6C3AED",
    "count": 1
  },
  {
    "hex": "#FF3280",
    "count": 1
  }
]