[
  {
    "hex": "#333333",
    "count": 438
  },
  {
    "hex": "#000000",
    "count": 341
  },
  {
    "hex": "#FFFFFF",
    "count": 189
  },
  {
    "hex": "#20124D",
    "count": 118
  },
  {
    "hex": "#7B7394",
    "count": 60
  },
  {
    "hex": "#A9A0C4",
    "count": 45
  },
  {
    "hex": "#8068FF",
    "count": 44
  },
  {
    "hex": "#8AFFBC",
    "count": 21
  },
  {
    "hex": "#F1F5FF",
    "count": 4
  },
  {
    "hex": "#2D1B6B",
    "count": 4
  },
  {
    "hex": "#F4F5FF",
    "count": 2
  },
  {
    "hex": "#6C3AED",
    "count": 1
  },
  {
    "hex": "#FF3280",
    "count": 1
  }
]