{
  "title": "How to set up static IPs for Google BigQuery via VPC | Docs",
  "description": "Looking to set up static IPs for Google BigQuery via VPC? Our platform, Improvado, provides a complete data pipeline for large enterprises. Learn more today!",
  "ogTitle": "How to set up static IPs for Google BigQuery via VPC | Docs",
  "ogDescription": "Looking to set up static IPs for Google BigQuery via VPC? Our platform, Improvado, provides a complete data pipeline for large enterprises. Learn more today!",
  "ogImage": null,
  "ogType": "website",
  "twitterCard": "summary_large_image",
  "twitterTitle": null,
  "twitterImage": null,
  "favicon": "https://improvado.io/593ed35b7e7f144e5e0ec373/5cbe4057c0a50299b4b7bb69_fav.png",
  "themeColor": null,
  "viewport": "width=device-width, initial-scale=1",
  "canonical": "https://improvado.io/docs/how-to-set-up-static-ips-for-google-bigquery-via-vpc"
}