[
  {
    "hex": "#000000",
    "count": 371
  },
  {
    "hex": "#333333",
    "count": 365
  },
  {
    "hex": "#FFFFFF",
    "count": 98
  },
  {
    "hex": "#3D4D65",
    "count": 35
  },
  {
    "hex": "#F81984",
    "count": 35
  },
  {
    "hex": "#8068FF",
    "count": 20
  },
  {
    "hex": "#DDE8ED",
    "count": 8
  },
  {
    "hex": "#20124D",
    "count": 2
  },
  {
    "hex": "#E7E7E7",
    "count": 2
  },
  {
    "hex": "#6C3AED",
    "count": 1
  },
  {
    "hex": "#FF3280",
    "count": 1
  }
]