[
  {
    "hex": "#000000",
    "count": 346
  },
  {
    "hex": "#333333",
    "count": 300
  },
  {
    "hex": "#FFFFFF",
    "count": 96
  },
  {
    "hex": "#8068FF",
    "count": 95
  },
  {
    "hex": "#20124D",
    "count": 32
  },
  {
    "hex": "#444D66",
    "count": 5
  },
  {
    "hex": "#F7F8FC",
    "count": 1
  },
  {
    "hex": "#FFD3F0",
    "count": 1
  },
  {
    "hex": "#FBFCCA",
    "count": 1
  },
  {
    "hex": "#C3F7BE",
    "count": 1
  },
  {
    "hex": "#6C3AED",
    "count": 1
  },
  {
    "hex": "#FF3280",
    "count": 1
  }
]